yacl.py
yacl-0.6.1.dist-info/LICENSE
yacl-0.6.1.dist-info/METADATA
yacl-0.6.1.dist-info/WHEEL
yacl-0.6.1.dist-info/top_level.txt
yacl-0.6.1.dist-info/RECORD
