Metadata-Version: 2.2
Name: yacl
Version: 0.6.1
Summary: YACL (Yet Another Color Logger) is a simple to use color logger for Python programs.
Author-email: Ingo Meyer <i.meyer@fz-juelich.de>
Maintainer-email: Ingo Meyer <i.meyer@fz-juelich.de>
License: Copyright 2019 Forschungszentrum Jülich GmbH
Project-URL: Homepage, https://github.com/IngoMeyer441/yacl
Keywords: utility,logging,color
Classifier: Development Status :: 5 - Production/Stable
Classifier: Environment :: Console
Classifier: Intended Audience :: Developers
Classifier: License :: OSI Approved :: MIT License
Classifier: Operating System :: MacOS
Classifier: Operating System :: POSIX :: Linux
Classifier: Programming Language :: Python
Classifier: Programming Language :: Python :: 3
Classifier: Programming Language :: Python :: 3.9
Classifier: Programming Language :: Python :: 3.10
Classifier: Programming Language :: Python :: 3.11
Classifier: Programming Language :: Python :: 3.12
Classifier: Programming Language :: Python :: 3.13
Classifier: Programming Language :: Python :: 3 :: Only
Classifier: Topic :: Software Development
Classifier: Topic :: Utilities
Requires-Python: >=3.9
License-File: LICENSE
Provides-Extra: colored-exceptions
Requires-Dist: pygments; extra == "colored-exceptions"
